filetrans/__init__.py
filetrans/cli.py
filetrans/client/__init__.py
filetrans/client/api.py
filetrans/server/__init__.py
filetrans/server/config.py
filetrans/server/database.py
filetrans/server/janitor.py
filetrans/server/jrpc.py
filetrans/server/main.py
filetrans/server/models.py
filetrans/server/storage/__init__.py
filetrans/server/storage/base.py
filetrans/server/storage/local.py
filetrans/server/storage/s3.py
filetrans/web/__init__.py
ft_dev-1.0.1.dist-info/METADATA
ft_dev-1.0.1.dist-info/WHEEL
ft_dev-1.0.1.dist-info/entry_points.txt
ft_dev-1.0.1.dist-info/top_level.txt
ft_dev-1.0.1.dist-info/RECORD
