Metadata-Version: 2.4
Name: ft-dev
Version: 1.0.1
Summary: Modern file transfer tool with CLI and jRPC API - Development Edition
Author-email: Jimmyki <jimmyki@xctf.org>
License-Expression: MIT
Project-URL: Homepage, https://github.com/jimmyki/filetrans
Project-URL: Repository, https://github.com/jimmyki/filetrans.git
Project-URL: Documentation, https://github.com/jimmyki/filetrans/blob/main/README.md
Project-URL: Bug Tracker, https://github.com/jimmyki/filetrans/issues
Keywords: file-transfer,jrpc,cli,cloudflare,r2,cdn,ft-dev
Classifier: Development Status :: 4 - Beta
Classifier: Intended Audience :: Developers
Classifier: Intended Audience :: End Users/Desktop
Classifier: Programming Language :: Python :: 3.10
Classifier: Programming Language :: Python :: 3.11
Classifier: Programming Language :: Python :: 3.12
Classifier: Topic :: Communications :: File Sharing
Classifier: Topic :: Utilities
Classifier: Environment :: Console
Requires-Python: >=3.10
Requires-Dist: typer[all]>=0.9.0
Requires-Dist: rich>=13.0.0
Requires-Dist: requests>=2.28.0
Requires-Dist: humanize>=4.0.0
Requires-Dist: pyperclip>=1.8.0
Requires-Dist: fastapi>=0.100.0
Requires-Dist: uvicorn[standard]>=0.23.0
Requires-Dist: pydantic>=2.0.0
Requires-Dist: sqlalchemy>=2.0.0
Requires-Dist: jinja2>=3.1.0
Requires-Dist: boto3>=1.28.0
Requires-Dist: bcrypt>=4.0.0
Requires-Dist: cryptography>=41.0.0
Provides-Extra: dev
Requires-Dist: pytest>=7.0.0; extra == "dev"
Requires-Dist: pytest-asyncio>=0.21.0; extra == "dev"
Requires-Dist: pytest-cov>=4.0.0; extra == "dev"
Requires-Dist: black>=23.0.0; extra == "dev"
Requires-Dist: ruff>=0.1.0; extra == "dev"
Requires-Dist: mypy>=1.0.0; extra == "dev"
Provides-Extra: clipboard
Requires-Dist: pyclip>=0.7.0; extra == "clipboard"
Provides-Extra: all
Requires-Dist: ft-dev[clipboard,dev]; extra == "all"
